nft_generator/Collection.py
nft_generator/Combination.py
nft_generator/Layer.py
nft_generator/LayerItem.py
nft_generator/Printers.py
nft_generator/__init__.py
nft_generator/__main__.py
nft_generator/constants.py
nft_generator/kernels.py
nft_generator-1.1.0.dist-info/METADATA
nft_generator-1.1.0.dist-info/WHEEL
nft_generator-1.1.0.dist-info/top_level.txt
nft_generator-1.1.0.dist-info/RECORD
