Metadata-Version: 2.1
Name: nft-generator
Version: 1.1.0
Summary: NFT Generator
Author-email: Quan Fan <fanquan@yuzj010.com>
Classifier: Programming Language :: Python :: 3
Requires-Python: >=3.7
Requires-Dist: opencv-python
Requires-Dist: numpy
Requires-Dist: multipledispatch
